{
  "cli": {
    "version": ">= 15.0.0",
    "appVersionSource": "remote"
  },
  "build": {
    "preview": {
      "distribution": "internal",
      "android": {
        "buildType": "apk"
      },
      "env": {
        "EXPO_PUBLIC_APP_ENV": "production",
        "EXPO_PUBLIC_API_URL": "https://dressgenius-api.fly.dev/api"
      }
    },
    "production": {
      "distribution": "store",
      "env": {
        "EXPO_PUBLIC_APP_ENV": "production",
        "EXPO_PUBLIC_API_URL": "https://dressgenius-api.fly.dev/api"
      }
    }
  }
}
